wreck/__init__.py
wreck/_package_installed.py
wreck/_package_installed.pyi
wreck/_run_cmd.py
wreck/_run_cmd.pyi
wreck/_safe_path.py
wreck/_safe_path.pyi
wreck/_version.py
wreck/_version.pyi
wreck/check_type.py
wreck/check_type.pyi
wreck/cli_dependencies.py
wreck/cli_dependencies.pyi
wreck/constants.py
wreck/constants.pyi
wreck/exceptions.py
wreck/exceptions.pyi
wreck/lock_collections.py
wreck/lock_collections.pyi
wreck/lock_compile.py
wreck/lock_compile.pyi
wreck/lock_datum.py
wreck/lock_datum.pyi
wreck/lock_discrepancy.py
wreck/lock_discrepancy.pyi
wreck/lock_filepins.py
wreck/lock_filepins.pyi
wreck/lock_fixing.py
wreck/lock_fixing.pyi
wreck/lock_loader.py
wreck/lock_loader.pyi
wreck/lock_util.py
wreck/lock_util.pyi
wreck/pep518_read.py
wreck/pep518_read.pyi
wreck/pep518_venvs.py
wreck/pep518_venvs.pyi
wreck/py.typed
wreck/monkey/__init__.py
wreck/monkey/patch_pyproject_reading.py
wreck/monkey/patch_pyproject_reading.pyi
wreck/monkey/pyproject_reading.py
wreck/monkey/pyproject_reading.pyi
wreck-0.3.5.dist-info/licenses/LICENSE
wreck-0.3.5.dist-info/licenses/NOTICE.txt
wreck-0.3.5.dist-info/METADATA
wreck-0.3.5.dist-info/WHEEL
wreck-0.3.5.dist-info/entry_points.txt
wreck-0.3.5.dist-info/top_level.txt
wreck-0.3.5.dist-info/RECORD
