Metadata-Version: 2.4
Name: wreck
Version: 0.3.5
Summary: Manage and fix requirements files for Python package authors
Author-email: Dave Faulkmore <faulkmore@protonmail.com>
License-Expression: AGPL-3.0-or-later
Project-URL: Documentation, https://msftcangoblowm.github.io/wreck
Project-URL: Docs (rtd), https://wreck.readthedocs.io/en/stable
Project-URL: Changes, https://raw.githubusercontent.com/msftcangoblowm/wreck/master/CHANGES.rst
Project-URL: PyPI Releases, https://pypi.org/project/wreck
Project-URL: Source code, https://github.com/msftcangoblowm/wreck
Project-URL: Issue tracker, https://github.com/msftcangoblowm/wreck/issues
Project-URL: Mastodon, https://mastodon.social/@msftcangoblowme
Keywords: pip,pip-tools,requirements,constraints
Classifier: Environment :: Console
Classifier: Development Status :: 3 - Alpha
Classifier: Intended Audience :: Developers
Classifier: Operating System :: OS Independent
Classifier: Programming Language :: Python :: 3
Classifier: Programming Language :: Python :: 3.9
Classifier: Programming Language :: Python :: 3.10
Classifier: Programming Language :: Python :: 3.11
Classifier: Programming Language :: Python :: 3.12
Classifier: Programming Language :: Python :: 3.13
Classifier: Programming Language :: Python :: Implementation :: CPython
Classifier: Programming Language :: Python :: Implementation :: PyPy
Classifier: Topic :: Software Development :: Build Tools
Classifier: Typing :: Typed
Requires-Python: >=3.9
License-File: LICENSE
License-File: NOTICE.txt
Requires-Dist: click==8.1.7; python_version < "3.10"
Requires-Dist: click==8.2.0; python_version >= "3.10"
Requires-Dist: importlib-metadata>=8.7.0
Requires-Dist: logging-strict>=1.6.1
Requires-Dist: packaging
Requires-Dist: pip-requirements-parser
Requires-Dist: pip-tools
Provides-Extra: pip
Requires-Dist: packaging==25.0; extra == "pip"
Requires-Dist: tomli==2.2.1; python_version < "3.11" and extra == "pip"
Requires-Dist: typing-extensions==4.12.2; python_version < "3.11" and extra == "pip"
Provides-Extra: pip-tools
Requires-Dist: click==8.1.7; python_version < "3.10" and extra == "pip-tools"
Requires-Dist: click==8.2.0; python_version >= "3.10" and extra == "pip-tools"
Requires-Dist: importlib-metadata==8.7.0; extra == "pip-tools"
Requires-Dist: packaging==25.0; extra == "pip-tools"
Requires-Dist: pip-tools==7.4.1; extra == "pip-tools"
Requires-Dist: pyproject-hooks==1.2.0; extra == "pip-tools"
Requires-Dist: tomli==2.2.1; python_version < "3.11" and extra == "pip-tools"
Requires-Dist: zipp==3.21.0; extra == "pip-tools"
Provides-Extra: dev
Requires-Dist: appdirs==1.4.4; extra == "dev"
Requires-Dist: attrs==24.2.0; extra == "dev"
Requires-Dist: backports-tarfile==1.2.0; extra == "dev"
Requires-Dist: black==24.10.0; extra == "dev"
Requires-Dist: blackdoc==0.3.9; extra == "dev"
Requires-Dist: certifi==2025.4.26; extra == "dev"
Requires-Dist: cffi==1.17.1; extra == "dev"
Requires-Dist: charset-normalizer==3.4.0; extra == "dev"
Requires-Dist: click==8.1.7; python_version < "3.10" and extra == "dev"
Requires-Dist: click==8.2.0; python_version >= "3.10" and extra == "dev"
Requires-Dist: coverage==7.6.10; extra == "dev"
Requires-Dist: cryptography==45.0.2; extra == "dev"
Requires-Dist: docutils==0.21.2; extra == "dev"
Requires-Dist: exceptiongroup==1.2.2; extra == "dev"
Requires-Dist: fastjsonschema==2.21.1; extra == "dev"
Requires-Dist: flake8==7.1.1; extra == "dev"
Requires-Dist: flake8-pyi==24.9.0; extra == "dev"
Requires-Dist: flake8-pyproject==1.2.3; extra == "dev"
Requires-Dist: idna==3.10; extra == "dev"
Requires-Dist: importlib-metadata==8.7.0; extra == "dev"
Requires-Dist: iniconfig==2.0.0; extra == "dev"
Requires-Dist: isort==5.13.2; extra == "dev"
Requires-Dist: jaraco-classes==3.4.0; extra == "dev"
Requires-Dist: jaraco-context==6.0.1; extra == "dev"
Requires-Dist: jaraco-functools==4.1.0; extra == "dev"
Requires-Dist: jeepney==0.8.0; extra == "dev"
Requires-Dist: keyring==25.5.0; extra == "dev"
Requires-Dist: logging-strict==1.6.1; extra == "dev"
Requires-Dist: markdown-it-py==3.0.0; extra == "dev"
Requires-Dist: mccabe==0.7.0; extra == "dev"
Requires-Dist: mdurl==0.1.2; extra == "dev"
Requires-Dist: more-itertools==10.6.0; extra == "dev"
Requires-Dist: mypy==1.15.0; extra == "dev"
Requires-Dist: mypy-extensions==1.0.0; extra == "dev"
Requires-Dist: nh3==0.2.17; extra == "dev"
Requires-Dist: packaging==25.0; extra == "dev"
Requires-Dist: pathspec==0.12.1; extra == "dev"
Requires-Dist: pip-requirements-parser==32.0.1; extra == "dev"
Requires-Dist: pip-tools==7.4.1; extra == "dev"
Requires-Dist: pkginfo==1.10.0; extra == "dev"
Requires-Dist: platformdirs==4.3.6; extra == "dev"
Requires-Dist: pluggy==1.6.0; extra == "dev"
Requires-Dist: pycodestyle==2.12.1; extra == "dev"
Requires-Dist: pycparser==2.22; extra == "dev"
Requires-Dist: pyflakes==3.2.0; extra == "dev"
Requires-Dist: pygments==2.19.1; extra == "dev"
Requires-Dist: pyparsing==3.2.0; extra == "dev"
Requires-Dist: pyproject-hooks==1.2.0; extra == "dev"
Requires-Dist: pytest==8.3.4; extra == "dev"
Requires-Dist: pytest-datadir==1.5.0; extra == "dev"
Requires-Dist: pytest-logging-strict==0.2.3; extra == "dev"
Requires-Dist: pytest-regressions==2.5.0; extra == "dev"
Requires-Dist: python-dateutil==2.9.0.post0; extra == "dev"
Requires-Dist: pyyaml==6.0.2; extra == "dev"
Requires-Dist: readme-renderer==44.0; extra == "dev"
Requires-Dist: requests==2.32.3; extra == "dev"
Requires-Dist: requests-toolbelt==1.0.0; extra == "dev"
Requires-Dist: rfc3986==2.0.0; extra == "dev"
Requires-Dist: rich==13.9.4; extra == "dev"
Requires-Dist: secretstorage==3.3.3; extra == "dev"
Requires-Dist: six==1.17.0; extra == "dev"
Requires-Dist: strictyaml==1.7.3; extra == "dev"
Requires-Dist: tomli==2.2.1; python_version < "3.11" and extra == "dev"
Requires-Dist: twine==5.1.1; extra == "dev"
Requires-Dist: types-setuptools==78.1.0.20250329; extra == "dev"
Requires-Dist: typing-extensions==4.12.2; python_version < "3.11" and extra == "dev"
Requires-Dist: urllib3==2.2.3; extra == "dev"
Requires-Dist: validate-pyproject==0.24.1; extra == "dev"
Requires-Dist: zipp==3.21.0; extra == "dev"
Provides-Extra: manage
Requires-Dist: appdirs==1.4.4; extra == "manage"
Requires-Dist: attrs==24.2.0; extra == "manage"
Requires-Dist: cachetools==5.5.0; extra == "manage"
Requires-Dist: cfgv==3.4.0; extra == "manage"
Requires-Dist: chardet==5.2.0; extra == "manage"
Requires-Dist: click==8.1.7; python_version < "3.10" and extra == "manage"
Requires-Dist: click==8.2.0; python_version >= "3.10" and extra == "manage"
Requires-Dist: colorama==0.4.6; extra == "manage"
Requires-Dist: distlib==0.3.9; extra == "manage"
Requires-Dist: filelock==3.16.1; extra == "manage"
Requires-Dist: identify==2.6.5; extra == "manage"
Requires-Dist: importlib-metadata==8.7.0; extra == "manage"
Requires-Dist: logging-strict==1.6.1; extra == "manage"
Requires-Dist: nodeenv==1.9.1; extra == "manage"
Requires-Dist: packaging==25.0; extra == "manage"
Requires-Dist: pip-requirements-parser==32.0.1; extra == "manage"
Requires-Dist: pip-tools==7.4.1; extra == "manage"
Requires-Dist: platformdirs==4.3.6; extra == "manage"
Requires-Dist: pluggy==1.6.0; extra == "manage"
Requires-Dist: pre-commit==4.0.1; extra == "manage"
Requires-Dist: pyparsing==3.2.0; extra == "manage"
Requires-Dist: pyproject-api==1.9.1; extra == "manage"
Requires-Dist: pyproject-hooks==1.2.0; extra == "manage"
Requires-Dist: python-dateutil==2.9.0.post0; extra == "manage"
Requires-Dist: pyyaml==6.0.2; extra == "manage"
Requires-Dist: six==1.17.0; extra == "manage"
Requires-Dist: strictyaml==1.7.3; extra == "manage"
Requires-Dist: tomli==2.2.1; python_version < "3.11" and extra == "manage"
Requires-Dist: tox==4.23.2; extra == "manage"
Requires-Dist: tox-gh-actions==3.2.0; extra == "manage"
Requires-Dist: typing-extensions==4.12.2; python_version < "3.11" and extra == "manage"
Requires-Dist: virtualenv==20.29.0; extra == "manage"
Requires-Dist: zipp==3.21.0; extra == "manage"
Provides-Extra: docs
Requires-Dist: alabaster==1.0.0; extra == "docs"
Requires-Dist: anyio==4.8.0; extra == "docs"
Requires-Dist: appdirs==1.4.4; extra == "docs"
Requires-Dist: attrs==24.2.0; extra == "docs"
Requires-Dist: babel==2.16.0; extra == "docs"
Requires-Dist: certifi==2025.4.26; extra == "docs"
Requires-Dist: charset-normalizer==3.4.2; extra == "docs"
Requires-Dist: click-log==0.4.0; extra == "docs"
Requires-Dist: colorama==0.4.6; extra == "docs"
Requires-Dist: docutils==0.21.2; extra == "docs"
Requires-Dist: dom-toml==2.0.0; extra == "docs"
Requires-Dist: domdf-python-tools==3.9.0; extra == "docs"
Requires-Dist: exceptiongroup==1.2.2; extra == "docs"
Requires-Dist: h11==0.14.0; extra == "docs"
Requires-Dist: idna==3.10; extra == "docs"
Requires-Dist: imagesize==1.4.1; extra == "docs"
Requires-Dist: importlib-metadata==8.7.0; extra == "docs"
Requires-Dist: interrogate==1.7.0; extra == "docs"
Requires-Dist: jinja2==3.1.5; extra == "docs"
Requires-Dist: jsonschema==4.23.0; extra == "docs"
Requires-Dist: jsonschema-specifications==2024.10.1; extra == "docs"
Requires-Dist: logging-strict==1.6.1; extra == "docs"
Requires-Dist: markdown-it-py==3.0.0; extra == "docs"
Requires-Dist: markupsafe==3.0.2; extra == "docs"
Requires-Dist: mdit-py-plugins==0.4.2; extra == "docs"
Requires-Dist: mdurl==0.1.2; extra == "docs"
Requires-Dist: myst-parser==4.0.0; extra == "docs"
Requires-Dist: natsort==8.4.0; extra == "docs"
Requires-Dist: packaging==25.0; extra == "docs"
Requires-Dist: pip-requirements-parser==32.0.1; extra == "docs"
Requires-Dist: pip-tools==7.4.1; extra == "docs"
Requires-Dist: py==1.11.0; extra == "docs"
Requires-Dist: pygments==2.19.1; extra == "docs"
Requires-Dist: pyparsing==3.2.0; extra == "docs"
Requires-Dist: pyproject-hooks==1.2.0; extra == "docs"
Requires-Dist: python-dateutil==2.9.0.post0; extra == "docs"
Requires-Dist: pyyaml==6.0.2; extra == "docs"
Requires-Dist: referencing==0.35.1; extra == "docs"
Requires-Dist: requests==2.32.3; extra == "docs"
Requires-Dist: rpds-py==0.22.3; extra == "docs"
Requires-Dist: scriv==1.5.1; extra == "docs"
Requires-Dist: six==1.17.0; extra == "docs"
Requires-Dist: sniffio==1.3.1; extra == "docs"
Requires-Dist: snowballstemmer==2.2.0; extra == "docs"
Requires-Dist: sphinx==8.1.3; extra == "docs"
Requires-Dist: sphinx-autobuild==2024.10.3; extra == "docs"
Requires-Dist: sphinx-copybutton==0.5.2; extra == "docs"
Requires-Dist: sphinx-design==0.6.1; extra == "docs"
Requires-Dist: sphinx-external-toc-strict==2.0.3.post5; extra == "docs"
Requires-Dist: sphinx-favicon==1.0.1; extra == "docs"
Requires-Dist: sphinx-paramlinks==0.6.0; extra == "docs"
Requires-Dist: sphinx-pyproject==0.3.0; extra == "docs"
Requires-Dist: sphinx-tabs==3.4.7; extra == "docs"
Requires-Dist: sphinxcontrib-applehelp==2.0.0; extra == "docs"
Requires-Dist: sphinxcontrib-devhelp==2.0.0; extra == "docs"
Requires-Dist: sphinxcontrib-htmlhelp==2.1.0; extra == "docs"
Requires-Dist: sphinxcontrib-jsmath==1.0.1; extra == "docs"
Requires-Dist: sphinxcontrib-qthelp==2.0.0; extra == "docs"
Requires-Dist: sphinxcontrib-serializinghtml==2.0.0; extra == "docs"
Requires-Dist: sphobjinv==2.3.1.2; extra == "docs"
Requires-Dist: starlette==0.45.2; extra == "docs"
Requires-Dist: strictyaml==1.7.3; extra == "docs"
Requires-Dist: tabulate==0.9.0; extra == "docs"
Requires-Dist: tomli==2.2.1; python_version < "3.11" and extra == "docs"
Requires-Dist: typing-extensions==4.12.2; python_version < "3.11" and extra == "docs"
Requires-Dist: urllib3==2.2.3; extra == "docs"
Requires-Dist: uvicorn==0.34.0; extra == "docs"
Requires-Dist: watchfiles==1.0.4; extra == "docs"
Requires-Dist: websockets==14.1; extra == "docs"
Requires-Dist: zipp==3.21.0; extra == "docs"
Dynamic: license-file
